[{"Title":"Apple","Ticker":"AAPL","StockPrice":491,"Safety":10,"StockPriceHistory":[500,491],"IsBankrupt":false},{"Title":"Google","Ticker":"GOOG","StockPrice":238,"Safety":8,"StockPriceHistory":[250,238],"IsBankrupt":false},{"Title":"Amazon","Ticker":"AMAZ","StockPrice":1210,"Safety":9,"StockPriceHistory":[1200,1210],"IsBankrupt":false},{"Title":"Tesla","Ticker":"TESL","StockPrice":940,"Safety":6,"StockPriceHistory":[900,940],"IsBankrupt":false},{"Title":"Kontur","Ticker":"KNTR","StockPrice":172,"Safety":7,"StockPriceHistory":[200,172],"IsBankrupt":false},{"Title":"Adobe","Ticker":"ADBE","StockPrice":208,"Safety":5,"StockPriceHistory":[250,208],"IsBankrupt":false},{"Title":"Yandex","Ticker":"YAAN","StockPrice":135,"Safety":4,"StockPriceHistory":[100,135],"IsBankrupt":false},{"Title":"Microsoft","Ticker":"MICR","StockPrice":1480,"Safety":7,"StockPriceHistory":[1500,1480],"IsBankrupt":false},{"Title":"JetBrains","Ticker":"JEBR","StockPrice":1310,"Safety":6,"StockPriceHistory":[1300,1310],"IsBankrupt":false}]